voluxgui/__init__.py
voluxgui/__main__.py
voluxgui/gui.py
voluxgui/launch.py
voluxgui-0.1.0.dist-info/METADATA
voluxgui-0.1.0.dist-info/WHEEL
voluxgui-0.1.0.dist-info/entry_points.txt
voluxgui-0.1.0.dist-info/top_level.txt
voluxgui-0.1.0.dist-info/RECORD
