Metadata-Version: 2.1
Name: voluxgui
Version: 0.1.0
Summary: volux module which provides a gui for volux itself
Home-page: UNKNOWN
Author: Denver Pallis
Author-email: DenverPallisProjects@gmail.com
License: GPLv3+
Platform: UNKNOWN
Requires-Python: >=3
Requires-Dist: volux (<1.0.0,>=0.9.16)
